{
  "project_info": {
    "project_number": "998072967693",
    "project_id": "share-blood-c3302",
    "storage_bucket": "share-blood-c3302.appspot.com"
  },
  "client": [
    {
      "client_info": {
        "mobilesdk_app_id": "1:998072967693:android:a74980186f58645a75ab44",
        "android_client_info": {
          "package_name": "com.example.shareblood"
        }
      },
      "oauth_client": [
        {
          "client_id": "998072967693-t54kirsboje9qb1acd8kb1e17cuqvv34.apps.googleusercontent.com",
          "client_type": 3
        }
      ],
      "api_key": [
        {
          "current_key": "AIzaSyCm1Um6x2DsirIuVK1pqfasB8IeThdXHOs"
        }
      ],
      "services": {
        "appinvite_service": {
          "other_platform_oauth_client": [
            {
              "client_id": "998072967693-t54kirsboje9qb1acd8kb1e17cuqvv34.apps.googleusercontent.com",
              "client_type": 3
            }
          ]
        }
      }
    }
  ],
  "configuration_version": "1"
}